mugbem/__init__.py
mugbem/__main__.py
mugbem/gui.py
mugbem/bitfinex/__init__.py
mugbem/bitfinex/watcher/__init__.py
mugbem/bitfinex/watcher/book_watcher.py
mugbem/bitfinex/watcher/base/__init__.py
mugbem/bitfinex/watcher/base/abstract_watcher.py
mugbem/bitfinex/watcher/base/requests/__init__.py
mugbem/bitfinex/watcher/base/requests/book_subscribe.py
mugbem/bitfinex/watcher/base/requests/base/__init__.py
mugbem/bitfinex/watcher/base/requests/base/abstract_request.py
mugbem/bitfinex/watcher/processor/__init__.py
mugbem/bitfinex/watcher/processor/book_processor.py
mugbem/bitfinex/watcher/processor/base/__init__.py
mugbem/bitfinex/watcher/processor/base/abstract_processor.py
mugbem-4.2.0.1.dist-info/METADATA
mugbem-4.2.0.1.dist-info/WHEEL
mugbem-4.2.0.1.dist-info/top_level.txt
mugbem-4.2.0.1.dist-info/RECORD
